LICENSE
MANIFEST.in
README.md
pyproject.toml
setup.cfg
setup.py
wagtail_showables/__init__.py
wagtail_showables/apps.py
wagtail_showables/backends.py
wagtail_showables/decorators.py
wagtail_showables/middleware.py
wagtail_showables/models.py
wagtail_showables/options.py
wagtail_showables/registry.py
wagtail_showables/views.py
wagtail_showables/wagtail_hooks.py
wagtail_showables.egg-info/PKG-INFO
wagtail_showables.egg-info/SOURCES.txt
wagtail_showables.egg-info/dependency_links.txt
wagtail_showables.egg-info/requires.txt
wagtail_showables.egg-info/top_level.txt
wagtail_showables/migrations/0001_initial.py
wagtail_showables/migrations/0002_wagtailshowablespermissions.py
wagtail_showables/migrations/__init__.py
wagtail_showables/migrations/__pycache__/0001_initial.cpython-311.pyc
wagtail_showables/migrations/__pycache__/0002_wagtailshowablespermissions.cpython-311.pyc
wagtail_showables/migrations/__pycache__/__init__.cpython-311.pyc
wagtail_showables/static/wagtail_showables/css/showables.css
wagtail_showables/templates/wagtail_showables/block_form_template.html
wagtail_showables/templates/wagtail_showables/showables_admin_form.html
wagtail_showables/templates/wagtail_showables/showables_admin_list.html